utils/__init__.py
utils/general.py
ultralytics_yolo-0.0.1.dist-info/LICENSE
ultralytics_yolo-0.0.1.dist-info/METADATA
ultralytics_yolo-0.0.1.dist-info/WHEEL
ultralytics_yolo-0.0.1.dist-info/top_level.txt
ultralytics_yolo-0.0.1.dist-info/RECORD
