Metadata-Version: 2.1
Name: ultralytics-yolo
Version: 0.0.1
Summary: realtimecv Python package
Home-page: https://github.com/AyushExel/realtimecv
Author: Ayush Chaurasia
Author-email: ayush.chaurarsia@gmail.com
Keywords: machine-learning,deep-learning,ml,pytorch
Classifier: Development Status :: 5 - Production/Stable
Classifier: Intended Audience :: Developers
Classifier: Operating System :: OS Independent
Classifier: Topic :: Education
Classifier: Topic :: Scientific/Engineering
Classifier: Topic :: Scientific/Engineering :: Artificial Intelligence
Classifier: Topic :: Scientific/Engineering :: Image Recognition
Classifier: License :: OSI Approved :: GNU General Public License v3 (GPLv3)
Classifier: Programming Language :: Python :: 3.7
Classifier: Programming Language :: Python :: 3.8
Classifier: Programming Language :: Python :: 3.9
Requires-Python: >=3.7, <4
License-File: LICENSE
Requires-Dist: numpy (>=1.18.5)
Requires-Dist: build
Requires-Dist: twine
Provides-Extra: dev
Requires-Dist: check-manifest ; extra == 'dev'
Provides-Extra: test
Requires-Dist: coverage ; extra == 'test'
